rsa_ct_kip/client.py
rsa_ct_kip/common.py
rsa_ct_kip/ct_kip_prf_aes.py
rsa_ct_kip/fakeserver.py
rsa_ct_kip/rsaprivkey.pem
rsa_ct_kip-0.6.0.dist-info/LICENSE.txt
rsa_ct_kip-0.6.0.dist-info/METADATA
rsa_ct_kip-0.6.0.dist-info/WHEEL
rsa_ct_kip-0.6.0.dist-info/entry_points.txt
rsa_ct_kip-0.6.0.dist-info/top_level.txt
rsa_ct_kip-0.6.0.dist-info/RECORD
