Metadata-Version: 2.1
Name: rsa-ct-kip
Version: 0.6.0
Summary: Provision an RSA SecurID token with RSA's CT-KIP protocol
Home-page: https://github.com/dlenski/rsa_ct_kip
Author: Daniel Lenski
Author-email: dlenski@gmail.com
License: MIT
Platform: UNKNOWN
License-File: LICENSE.txt
Requires-Dist: pycryptodome (>=3.4.7)
Requires-Dist: requests (>=2.0)
